websocket/__init__.py
websocket/_abnf.py
websocket/_app.py
websocket/_cookiejar.py
websocket/_core.py
websocket/_exceptions.py
websocket/_handshake.py
websocket/_http.py
websocket/_logging.py
websocket/_socket.py
websocket/_ssl_compat.py
websocket/_url.py
websocket/_utils.py
websocket/tests/__init__.py
websocket/tests/test_cookiejar.py
websocket/tests/test_websocket.py
websocket/tests/data/header01.txt
websocket/tests/data/header02.txt
websocket_client_temp-0.57.1.data/scripts/wsdump.py
websocket_client_temp-0.57.1.dist-info/LICENSE
websocket_client_temp-0.57.1.dist-info/METADATA
websocket_client_temp-0.57.1.dist-info/WHEEL
websocket_client_temp-0.57.1.dist-info/top_level.txt
websocket_client_temp-0.57.1.dist-info/RECORD
